ellipticipy/__init__.py
ellipticipy/main.py
ellipticipy/tools.py
ellipticipy-1.0.0.dist-info/LICENSE
ellipticipy-1.0.0.dist-info/METADATA
ellipticipy-1.0.0.dist-info/WHEEL
ellipticipy-1.0.0.dist-info/top_level.txt
ellipticipy-1.0.0.dist-info/RECORD
