Metadata-Version: 2.1
Name: ellipticipy
Version: 1.0.0
Summary: Package for the calculation of ellipticity corrections for teleseismic waves
Home-page: https://github.com/StuartJRussell/EllipticiPy
Author: Stuart Russell, John F. Rudge, Jessica C. E. Irving, Sanne Cottaar
Author-email: sr895@cam.ac.uk
Project-URL: Bug Tracker, https://github.com/StuartJRussell/EllipticiPy/issues
Classifier: Programming Language :: Python :: 3
Classifier: License :: OSI Approved :: GNU Lesser General Public License v3 (LGPLv3)
Classifier: Operating System :: OS Independent
Requires-Python: >=3.6
License-File: LICENSE
Requires-Dist: numpy
Requires-Dist: obspy
Requires-Dist: scipy
